mycelium/__init__.py
mycelium/client.py
mycelium/client_config.py
mycelium/config.py
mycelium/main.py
mycelium/api/__init__.py
mycelium/api/app.py
mycelium/api/client_app.py
mycelium/api/worker_models.py
mycelium/api/generated_sources/__init__.py
mycelium/api/generated_sources/server_schemas/__init__.py
mycelium/api/generated_sources/server_schemas/api_client.py
mycelium/api/generated_sources/server_schemas/api_response.py
mycelium/api/generated_sources/server_schemas/configuration.py
mycelium/api/generated_sources/server_schemas/exceptions.py
mycelium/api/generated_sources/server_schemas/rest.py
mycelium/api/generated_sources/server_schemas/api/__init__.py
mycelium/api/generated_sources/server_schemas/api/default_api.py
mycelium/api/generated_sources/server_schemas/models/__init__.py
mycelium/api/generated_sources/server_schemas/models/api_section.py
mycelium/api/generated_sources/server_schemas/models/chroma_section.py
mycelium/api/generated_sources/server_schemas/models/clap_section.py
mycelium/api/generated_sources/server_schemas/models/compute_on_server200_response.py
mycelium/api/generated_sources/server_schemas/models/compute_on_server_request.py
mycelium/api/generated_sources/server_schemas/models/compute_text_search_request.py
mycelium/api/generated_sources/server_schemas/models/config_request.py
mycelium/api/generated_sources/server_schemas/models/config_response.py
mycelium/api/generated_sources/server_schemas/models/create_playlist_request.py
mycelium/api/generated_sources/server_schemas/models/get_similar_by_track200_response.py
mycelium/api/generated_sources/server_schemas/models/library_stats_response.py
mycelium/api/generated_sources/server_schemas/models/logging_section.py
mycelium/api/generated_sources/server_schemas/models/media_server_section.py
mycelium/api/generated_sources/server_schemas/models/playlist_response.py
mycelium/api/generated_sources/server_schemas/models/plex_section.py
mycelium_ai-0.5.0.dist-info/licenses/LICENSE
mycelium_ai-0.5.0.dist-info/METADATA
mycelium_ai-0.5.0.dist-info/WHEEL
mycelium_ai-0.5.0.dist-info/entry_points.txt
mycelium_ai-0.5.0.dist-info/top_level.txt
mycelium_ai-0.5.0.dist-info/RECORD
