Metadata-Version: 2.4
Name: mycelium-ai
Version: 0.5.0
Summary: Plex collection creator and recommendation system using LAION-CLAP
Author-email: marceljungle <gigi.dan2011@gmail.com>
License: MIT
Project-URL: Homepage, https://github.com/marceljungle/mycelium
Project-URL: Repository, https://github.com/marceljungle/mycelium
Project-URL: Issues, https://github.com/marceljungle/mycelium/issues
Keywords: plex,music,recommendation,clap,ml
Classifier: Development Status :: 3 - Alpha
Classifier: Intended Audience :: Developers
Classifier: License :: OSI Approved :: MIT License
Classifier: Programming Language :: Python :: 3
Classifier: Programming Language :: Python :: 3.9
Classifier: Programming Language :: Python :: 3.10
Classifier: Programming Language :: Python :: 3.11
Classifier: Programming Language :: Python :: 3.12
Requires-Python: >=3.9
License-File: LICENSE
Requires-Dist: plexapi>=4.15.0
Requires-Dist: transformers>=4.30.0
Requires-Dist: torch>=2.0.0
Requires-Dist: librosa>=0.10.0
Requires-Dist: chromadb>=0.4.0
Requires-Dist: tqdm>=4.65.0
Requires-Dist: fastapi>=0.100.0
Requires-Dist: uvicorn>=0.23.0
Requires-Dist: python-multipart>=0.0.6
Requires-Dist: pydantic>=2.0.0
Requires-Dist: typer[all]>=0.16.0
Requires-Dist: requests>=2.31.0
Requires-Dist: urllib3<3,>=1.26
Requires-Dist: python-dateutil>=2.8.2
Requires-Dist: certifi>=2023.0.0
Provides-Extra: dev
Requires-Dist: pytest>=7.0.0; extra == "dev"
Requires-Dist: pytest-asyncio>=0.21.0; extra == "dev"
Requires-Dist: black>=23.0.0; extra == "dev"
Requires-Dist: isort>=5.12.0; extra == "dev"
Requires-Dist: mypy>=1.0.0; extra == "dev"
Dynamic: license-file
